uvicmuse/Backend.py
uvicmuse/MuseBLE.py
uvicmuse/MuseFinder.py
uvicmuse/MuseWrapper.py
uvicmuse/__init__.py
uvicmuse/__main__.py
uvicmuse/asynckivy.py
uvicmuse/constants.py
uvicmuse/helper.py
uvicmuse/interface.py
uvicmuse/muse.py
uvicmuse/muse_wrapper.py
uvicmuse/runner.py
uvicmuse/docs/Header.png
uvicmuse-5.3.3.dist-info/LICENSE.txt
uvicmuse-5.3.3.dist-info/METADATA
uvicmuse-5.3.3.dist-info/WHEEL
uvicmuse-5.3.3.dist-info/entry_points.txt
uvicmuse-5.3.3.dist-info/top_level.txt
uvicmuse-5.3.3.dist-info/RECORD
